modular_trader/__init__.py
modular_trader/allocation.py
modular_trader/context.py
modular_trader/record.py
modular_trader/signal.py
modular_trader/time.py
modular_trader/universe.py
modular_trader/common/__init__.py
modular_trader/common/constants.py
modular_trader/common/enums.py
modular_trader/common/type_aliases.py
modular_trader/common/utils.py
modular_trader/engine/__init__.py
modular_trader/engine/alpaca.py
modular_trader/engine/base.py
modular_trader/framework/__init__.py
modular_trader/framework/collection.py
modular_trader/framework/asset_selection/__init__.py
modular_trader/framework/asset_selection/base.py
modular_trader/framework/asset_selection/manual.py
modular_trader/framework/order_execution/__init__.py
modular_trader/framework/order_execution/base.py
modular_trader/framework/order_execution/instant.py
modular_trader/framework/order_execution/threshold.py
modular_trader/framework/portfolio_construction/__init__.py
modular_trader/framework/portfolio_construction/base.py
modular_trader/framework/portfolio_construction/equal.py
modular_trader/framework/risk_management/__init__.py
modular_trader/framework/risk_management/base.py
modular_trader/framework/risk_management/fixed.py
modular_trader/framework/risk_management/null.py
modular_trader/framework/signal_generation/__init__.py
modular_trader/framework/signal_generation/base.py
modular_trader/framework/signal_generation/constant.py
modular_trader/framework/signal_generation/null.py
modular_trader/indicator/__init__.py
modular_trader/indicator/handler/__init__.py
modular_trader/indicator/handler/alpaca.py
modular_trader/indicator/handler/base.py
modular_trader/indicator/technical/__init__.py
modular_trader/indicator/technical/base.py
modular_trader/indicator/technical/rsi.py
modular_trader/indicator/technical/settings.py
modular_trader/indicator/technical/sma.py
modular_trader/indicator/technical/stoch.py
modular_trader/logging/__init__.py
modular_trader/logging/base.py
modular_trader/logging/trade.py
modular_trader-0.0.3.dist-info/LICENSE
modular_trader-0.0.3.dist-info/METADATA
modular_trader-0.0.3.dist-info/WHEEL
modular_trader-0.0.3.dist-info/top_level.txt
modular_trader-0.0.3.dist-info/RECORD
