Metadata-Version: 2.1
Name: modular-trader
Version: 0.0.3
Summary: A Flexible Algorithmic Trading Framework
Author: Kachain Fuangsung
Author-email: kachain.f@outlook.com
License: MIT
Project-URL: Homepage, https://github.com/kfuangsung/modular-trader
Project-URL: Documentation, https://kfuangsung.github.io/modular-trader
Project-URL: Repository, https://github.com/kfuangsung/modular-trader
Project-URL: Changelog, https://github.com/kfuangsung/modular-trader/blob/main/CHANGELOG.md
Classifier: Programming Language :: Python :: 3
Classifier: Topic :: Office/Business :: Financial :: Investment
Classifier: License :: OSI Approved :: MIT License
Requires-Python: >=3.10
License-File: LICENSE
Requires-Dist: typing-extensions>=4.12.0
Requires-Dist: alpaca-py>=0.28.0
Requires-Dist: pydantic>=2.8.0
Requires-Dist: python-benedict>=0.33.0
Requires-Dist: multimethod>=1.12
Requires-Dist: talipp>=2.4.0
Requires-Dist: loguru>=0.7.2
Requires-Dist: pendulum>=3.0.0
Requires-Dist: python-dotenv>=1.0.0
